README.rst
setup.py
asheeshs_django_optimizer/__init__.py
asheeshs_django_optimizer/models.py
asheeshs_django_optimizer/urls.py
asheeshs_django_optimizer/views.py
asheeshs_django_optimizer.egg-info/PKG-INFO
asheeshs_django_optimizer.egg-info/SOURCES.txt
asheeshs_django_optimizer.egg-info/dependency_links.txt
asheeshs_django_optimizer.egg-info/top_level.txt