Metadata-Version: 1.1
Name: asheeshs-django-optimizer
Version: 1.2
Summary: A pretend Django optimizer for use in a web security tutorial
Home-page: UNKNOWN
Author: asheesh@asheesh.org
Author-email: UNKNOWN
License: Expat
Platform: UNKNOWN
Classifier: Development Status :: 3 - Alpha
Classifier: License :: OSI Approved :: MIT License
